oceanum/cli/prax/__init__.py
oceanum/cli/prax/client.py
oceanum/cli/prax/main.py
oceanum/cli/prax/models.py
oceanum/cli/prax/project.py
oceanum/cli/prax/route.py
oceanum/cli/prax/user.py
oceanum/cli/prax/utils.py
oceanum/cli/prax/workflows.py
oceanum_prax-0.9.2.dist-info/licenses/AUTHORS.rst
oceanum_prax-0.9.2.dist-info/licenses/LICENSE
oceanum_prax-0.9.2.dist-info/METADATA
oceanum_prax-0.9.2.dist-info/WHEEL
oceanum_prax-0.9.2.dist-info/entry_points.txt
oceanum_prax-0.9.2.dist-info/top_level.txt
oceanum_prax-0.9.2.dist-info/RECORD
