Metadata-Version: 2.4
Name: oceanum-prax
Version: 0.9.2
Summary: Command-line utility for Oceanum.io PRAX platform
Author-email: Oceanum Developers <developers@oceanum.science>
Maintainer-email: Oceanum Developers <developers@oceanum.science>
License: MIT License
Project-URL: Homepage, https://oceanum.io/
Project-URL: Source, https://github.com/oceanum-io/oceanum-run-cli
Project-URL: Documentation, https://oceanum-python.readthedocs.io/en/latest/
Project-URL: Tracker, https://github.com/oceanum-io/oceanum-run-cli/issues
Keywords: oceanum,datamesh,oceanum.io,prax,ci/cd
Classifier: Development Status :: 4 - Beta
Classifier: Intended Audience :: Science/Research
Classifier: License :: OSI Approved :: MIT License
Classifier: Natural Language :: English
Classifier: Operating System :: OS Independent
Classifier: Topic :: Scientific/Engineering
Classifier: Topic :: Software Development :: Build Tools
Classifier: Programming Language :: Python :: 3.10
Classifier: Programming Language :: Python :: 3.11
Classifier: Programming Language :: Python :: 3.12
Classifier: Programming Language :: Python :: 3.13
Requires-Python: >=3.10
License-File: LICENSE
License-File: AUTHORS.rst
Requires-Dist: click
Requires-Dist: platformdirs
Requires-Dist: pydantic[email]
Requires-Dist: python-jsonpath<2.0.0
Requires-Dist: requests
Requires-Dist: tabulate
Requires-Dist: humanize
Requires-Dist: oceanum>=1.0.11
Provides-Extra: test
Requires-Dist: pytest; extra == "test"
Requires-Dist: pytest-cov; extra == "test"
Requires-Dist: ruff; extra == "test"
Provides-Extra: modelgen
Requires-Dist: datamodel-code-generator[http]; extra == "modelgen"
Dynamic: license-file
